xj_migrate/__init__.py
xj_migrate/admin.py
xj_migrate/apps.py
xj_migrate/common.py
xj_migrate/models.py
xj_migrate/urls.py
xj_migrate/apis/__init__.py
xj_migrate/apis/data_excel.py
xj_migrate/apis/data_migration.py
xj_migrate/apis/export_api.py
xj_migrate/apis/import_api.py
xj_migrate/apis/migrate_foreign_key_mapping.py
xj_migrate/apis/migrate_platfrom.py
xj_migrate/management/__init__.py
xj_migrate/management/spider_base.py
xj_migrate/management/bx_bids_spiders/__init__.py
xj_migrate/management/bx_bids_spiders/guangxi_spider.py
xj_migrate/management/bx_bids_spiders/hangzhou_spider.py
xj_migrate/management/bx_bids_spiders/ningbo_spider.py
xj_migrate/management/commands/__init__.py
xj_migrate/management/commands/bx_spider.py
xj_migrate/management/commands/sync_configure.py
xj_migrate/management/data_clean/__init__.py
xj_migrate/services/DataConsolidation.py
xj_migrate/services/__init__.py
xj_migrate/services/data_execl_service.py
xj_migrate/services/data_execl_service2.py
xj_migrate/services/doc_export_service.py
xj_migrate/services/excel_export_service.py
xj_migrate/services/execl_import.py
xj_migrate/services/execl_import_copy1.py
xj_migrate/services/execl_service.py
xj_migrate/services/execl_service_copy.py
xj_migrate/services/mapping_process.py
xj_migrate/services/migrate_foregin_key_mapping_service.py
xj_migrate/services/migrate_platfrom_service.py
xj_migrate/utils/__init__.py
xj_migrate/utils/common.py
xj_migrate/utils/custom_authorization.py
xj_migrate/utils/custom_response.py
xj_migrate/utils/custom_tool.py
xj_migrate/utils/digit_algorithm.py
xj_migrate/utils/execl_import.py
xj_migrate/utils/j_config.py
xj_migrate/utils/j_dict.py
xj_migrate/utils/jconfig.py
xj_migrate/utils/model_handle.py
xj_migrate/utils/unionpay_utils.py
xj_migrate/utils/user_wrapper.py
xj_migrate/utils/utility_method.py
xj_migrate-1.0.22.dist-info/METADATA
xj_migrate-1.0.22.dist-info/WHEEL
xj_migrate-1.0.22.dist-info/top_level.txt
xj_migrate-1.0.22.dist-info/RECORD
