Metadata-Version: 2.1
Name: xj-migrate
Version: 1.0.22
Summary: 迁移模块
License: apache 3.0
Requires-Dist: sqlalchemy
Requires-Dist: pymysql
Requires-Dist: xlrd
Requires-Dist: xlutils
Requires-Dist: xlwt
Requires-Dist: docxtpl
